<?xml version="1.0" encoding="UTF-8"?>
<persistence xmlns="https://jakarta.ee/xml/ns/persistence"
             xmlns:xsi="http://www.w3.org/2001/XMLSchema-instance"
             xsi:schemaLocation="https://jakarta.ee/xml/ns/persistence
             https://jakarta.ee/xml/ns/persistence/persistence_3_0.xsd"
             version="3.0">

    <persistence-unit name="default" transaction-type="JTA">
        <provider>org.eclipse.persistence.jpa.PersistenceProvider</provider>
        <jta-data-source>jdbc/__default</jta-data-source>
        
        <!-- Entity classes -->
        <class>com.example.entity.Greeting</class>
        
        <!-- Exclude unlisted classes -->
        <exclude-unlisted-classes>true</exclude-unlisted-classes>
        
        <properties>
            <!-- Database Schema Generation -->
            <property name="jakarta.persistence.schema-generation.database.action" value="drop-and-create"/>
            <property name="jakarta.persistence.schema-generation.create-source" value="metadata"/>
            <property name="jakarta.persistence.schema-generation.drop-source" value="metadata"/>
            
            <!-- EclipseLink specific properties -->
            <property name="eclipselink.ddl-generation" value="create-tables"/>
            <property name="eclipselink.ddl-generation.output-mode" value="database"/>
            <property name="eclipselink.logging.level" value="INFO"/>
            <property name="eclipselink.logging.level.sql" value="FINE"/>
            <property name="eclipselink.logging.parameters" value="true"/>
            
            <!-- Connection Pool Settings -->
            <property name="eclipselink.connection-pool.default.initial" value="1"/>
            <property name="eclipselink.connection-pool.default.min" value="1"/>
            <property name="eclipselink.connection-pool.default.max" value="10"/>
            
            <!-- Cache Settings -->
            <property name="eclipselink.cache.shared.default" value="false"/>
            
            <!-- Validation -->
            <property name="eclipselink.jpa.uppercase-column-names" value="false"/>
        </properties>
    </persistence-unit>

    <!-- Alternative persistence unit for testing with H2 -->
    <persistence-unit name="test" transaction-type="RESOURCE_LOCAL">
        <provider>org.eclipse.persistence.jpa.PersistenceProvider</provider>
        
        <class>com.example.entity.Greeting</class>
        <exclude-unlisted-classes>true</exclude-unlisted-classes>
        
        <properties>
            <!-- H2 Database for testing -->
            <property name="jakarta.persistence.jdbc.driver" value="org.h2.Driver"/>
            <property name="jakarta.persistence.jdbc.url" value="jdbc:h2:mem:testdb;DB_CLOSE_DELAY=-1;DB_CLOSE_ON_EXIT=FALSE"/>
            <property name="jakarta.persistence.jdbc.user" value="sa"/>
            <property name="jakarta.persistence.jdbc.password" value=""/>
            
            <!-- Schema generation -->
            <property name="jakarta.persistence.schema-generation.database.action" value="drop-and-create"/>
            <property name="jakarta.persistence.schema-generation.create-source" value="metadata"/>
            <property name="jakarta.persistence.schema-generation.drop-source" value="metadata"/>
            
            <!-- EclipseLink settings -->
            <property name="eclipselink.ddl-generation" value="create-tables"/>
            <property name="eclipselink.ddl-generation.output-mode" value="database"/>
            <property name="eclipselink.logging.level" value="INFO"/>
            <property name="eclipselink.logging.level.sql" value="FINE"/>
            <property name="eclipselink.logging.parameters" value="true"/>
        </properties>
    </persistence-unit>

</persistence>
